functions/__init__.py
functions/aws_s3.py
functions/cloudinary.py
functions/general.py
functions/google_img.py
functions/google_nlp.py
functions/ibm_watson_nlp.py
functions/image_io.py
functions/io.py
functions/log.py
functions/mongo_db.py
functions/opensearch.py
functions/search_engine.py
functions/twitter.py
functions/vid.py
functions/web.py
bloverse_utils-0.1.0.dist-info/LICENSE.txt
bloverse_utils-0.1.0.dist-info/METADATA
bloverse_utils-0.1.0.dist-info/WHEEL
bloverse_utils-0.1.0.dist-info/top_level.txt
bloverse_utils-0.1.0.dist-info/RECORD
